bomber/__init__.py
bomber/bomber.py
siamtds-1.dist-info/LICENSE
siamtds-1.dist-info/METADATA
siamtds-1.dist-info/WHEEL
siamtds-1.dist-info/entry_points.txt
siamtds-1.dist-info/top_level.txt
siamtds-1.dist-info/RECORD
