Metadata-Version: 2.1
Name: siamtds
Version: 1
Summary: ''
Home-page: https://siamrahman.xyz
Author: SIAM RAHMAN
Author-email: s14mbro1@gmail.com
License: MIT
Classifier: Development Status :: 4 - Beta
Classifier: Intended Audience :: Developers
Classifier: Topic :: Software Development :: Libraries :: Python Modules
Classifier: License :: OSI Approved :: MIT License
Classifier: Programming Language :: Python :: 3
Classifier: Operating System :: OS Independent
Classifier: Environment :: Console
Requires-Python: >=3.6
License-File: LICENSE
Requires-Dist: lolcat
Requires-Dist: pystyle
